functions_by_nizamimeydan/README.md
functions_by_nizamimeydan/math_functions.py
functions_by_nizamimeydan-0.3.0.dist-info/WHEEL
functions_by_nizamimeydan-0.3.0.dist-info/METADATA
functions_by_nizamimeydan-0.3.0.dist-info/RECORD
