Metadata-Version: 2.1
Name: functions-by-nizamimeydan
Version: 0.3.0
Summary: 
Author: Meydan52
Author-email: nizamimeydan@gmail.com
Requires-Python: >=3.10,<4.0
Classifier: Programming Language :: Python :: 3
Classifier: Programming Language :: Python :: 3.10
Classifier: Programming Language :: Python :: 3.11
